{
  "queries": [
    {
      "name": "Unnamed Query",
      "execution_time": 0.157,
      "row_count": 1,
      "memory_start_mb": 84.91,
      "memory_end_mb": 84.91,
      "memory_delta_mb": 0.0,
      "timestamp": "2025-11-30T19:45:29.866079",
      "query_preview": "\n        WITH gdp_data AS (\n            SELECT\n                time_value,\n                data_value as gdp_growth,\n                LAG(data_value, 1) OVER (ORDER BY time_value) as prev_gdp,\n        ..."
    },
    {
      "name": "Unnamed Query",
      "execution_time": 0.148,
      "row_count": 90,
      "memory_start_mb": 84.91,
      "memory_end_mb": 84.91,
      "memory_delta_mb": 0.0,
      "timestamp": "2025-11-30T19:45:30.086502",
      "query_preview": "\n        SELECT\n            data_value,\n            time_value\n        FROM bok_economic_indicators\n        WHERE stat_code = '722Y001'\n            AND cycle = 'D'\n        ORDER BY time_value DESC\n   ..."
    },
    {
      "name": "Unnamed Query",
      "execution_time": 0.148,
      "row_count": 3,
      "memory_start_mb": 84.91,
      "memory_end_mb": 84.91,
      "memory_delta_mb": 0.0,
      "timestamp": "2025-11-30T19:45:30.307533",
      "query_preview": "\n        SELECT\n            data_value\n        FROM bok_economic_indicators\n        WHERE stat_code = '513Y001'\n            AND item_name1 LIKE '%경제심리지수%'\n            AND cycle = 'M'\n        ORDER BY ..."
    },
    {
      "name": "Unnamed Query",
      "execution_time": 0.145,
      "row_count": 30,
      "memory_start_mb": 84.91,
      "memory_end_mb": 84.91,
      "memory_delta_mb": 0.0,
      "timestamp": "2025-11-30T19:45:30.523950",
      "query_preview": "\n        SELECT\n            data_value,\n            time_value\n        FROM exchange_rate\n        WHERE stat_code = '731Y001'\n            AND item_code1 = '0000001'\n            AND cycle = 'D'\n       ..."
    },
    {
      "name": "Unnamed Query",
      "execution_time": 0.144,
      "row_count": 4,
      "memory_start_mb": 84.91,
      "memory_end_mb": 84.91,
      "memory_delta_mb": 0.0,
      "timestamp": "2025-11-30T19:45:30.741008",
      "query_preview": "\n        SELECT\n            data_value,\n            time_value\n        FROM bok_economic_indicators\n        WHERE stat_code = '901Y009'\n            AND cycle = 'M'\n        ORDER BY time_value DESC\n   ..."
    },
    {
      "name": "Unnamed Query",
      "execution_time": 0.147,
      "row_count": 1,
      "memory_start_mb": 84.91,
      "memory_end_mb": 84.91,
      "memory_delta_mb": 0.0,
      "timestamp": "2025-11-30T19:45:30.959798",
      "query_preview": "\n            WITH market_data AS (\n                SELECT\n                    close,\n                    LAG(close, 20) OVER (ORDER BY date) as close_20d_ago,\n                    LAG(close, 60) OVER (..."
    },
    {
      "name": "Unnamed Query",
      "execution_time": 0.073,
      "row_count": 1,
      "memory_start_mb": 84.91,
      "memory_end_mb": 84.91,
      "memory_delta_mb": 0.0,
      "timestamp": "2025-11-30T19:45:31.104657",
      "query_preview": "\n            WITH market_data AS (\n                SELECT\n                    close,\n                    LAG(close, 20) OVER (ORDER BY date) as close_20d_ago,\n                    LAG(close, 60) OVER (..."
    },
    {
      "name": "Unnamed Query",
      "execution_time": 2.041,
      "row_count": 163,
      "memory_start_mb": 84.91,
      "memory_end_mb": 84.95,
      "memory_delta_mb": 0.03,
      "timestamp": "2025-11-30T19:45:33.218647",
      "query_preview": "\n        WITH stock_returns AS (\n            SELECT\n                d.industry,\n                i.symbol,\n                i.date,\n                i.close,\n                LAG(i.close, 20) OVER (PARTIT..."
    },
    {
      "name": "Query 1: Basic Info",
      "execution_time": 0.388,
      "row_count": 2636,
      "memory_start_mb": 84.95,
      "memory_end_mb": 85.34,
      "memory_delta_mb": 0.4,
      "timestamp": "2025-11-30T19:45:33.677960",
      "query_preview": "\n        SELECT symbol, exchange, industry, theme\n        FROM kr_stock_detail\n        WHERE symbol = ANY($1)\n        "
    },
    {
      "name": "Query 2: Combined Market Data (Latest + Liquidity + Volatility)",
      "execution_time": 2.068,
      "row_count": 2750,
      "memory_start_mb": 85.35,
      "memory_end_mb": 85.73,
      "memory_delta_mb": 0.38,
      "timestamp": "2025-11-30T19:45:35.822650",
      "query_preview": "\n        WITH latest_data AS (\n            SELECT DISTINCT ON (symbol)\n                symbol,\n                market_cap,\n                close,\n                date\n            FROM kr_intraday_tota..."
    }
  ],
  "phases": {
    "phase1": 3.579948,
    "phase2": 2.617403,
    "phase2_5": 0.011729,
    "phase3": 0.076372
  },
  "memory_snapshots": [
    {
      "label": "Start",
      "timestamp": "2025-11-30T19:45:29.709368",
      "rss_mb": 84.91,
      "vms_mb": 435.84,
      "percent": 0.54
    },
    {
      "label": "After Phase 1",
      "timestamp": "2025-11-30T19:45:33.289492",
      "rss_mb": 84.95,
      "vms_mb": 435.84,
      "percent": 0.54
    },
    {
      "label": "After Phase 2",
      "timestamp": "2025-11-30T19:45:35.907134",
      "rss_mb": 86.23,
      "vms_mb": 436.89,
      "percent": 0.55
    },
    {
      "label": "After Phase 2.5",
      "timestamp": "2025-11-30T19:45:35.919048",
      "rss_mb": 86.62,
      "vms_mb": 437.24,
      "percent": 0.55
    },
    {
      "label": "After Phase 3",
      "timestamp": "2025-11-30T19:45:35.995618",
      "rss_mb": 87.11,
      "vms_mb": 437.24,
      "percent": 0.55
    }
  ],
  "start_time": "2025-11-30T19:45:29.709267",
  "end_time": "2025-11-30T19:45:35.995664",
  "total_time": 6.286397,
  "total_stocks": 2750,
  "processed_stocks": 2636,
  "skipped_stocks": 114
}