{
  "queries": [
    {
      "name": "Unnamed Query",
      "execution_time": 0.199,
      "row_count": 1,
      "memory_start_mb": 83.72,
      "memory_end_mb": 83.72,
      "memory_delta_mb": 0.0,
      "timestamp": "2025-11-20T06:12:21.012406",
      "query_preview": "\n        WITH gdp_data AS (\n            SELECT\n                time_value,\n                data_value as gdp_growth,\n                LAG(data_value, 1) OVER (ORDER BY time_value) as prev_gdp,\n        ..."
    },
    {
      "name": "Unnamed Query",
      "execution_time": 0.181,
      "row_count": 90,
      "memory_start_mb": 83.72,
      "memory_end_mb": 83.72,
      "memory_delta_mb": 0.0,
      "timestamp": "2025-11-20T06:12:21.283369",
      "query_preview": "\n        SELECT\n            data_value,\n            time_value\n        FROM bok_economic_indicators\n        WHERE stat_code = '722Y001'\n            AND cycle = 'D'\n        ORDER BY time_value DESC\n   ..."
    },
    {
      "name": "Unnamed Query",
      "execution_time": 0.191,
      "row_count": 3,
      "memory_start_mb": 83.72,
      "memory_end_mb": 83.72,
      "memory_delta_mb": 0.0,
      "timestamp": "2025-11-20T06:12:21.563796",
      "query_preview": "\n        SELECT\n            data_value\n        FROM bok_economic_indicators\n        WHERE stat_code = '513Y001'\n            AND item_name1 LIKE '%경제심리지수%'\n            AND cycle = 'M'\n        ORDER BY ..."
    },
    {
      "name": "Unnamed Query",
      "execution_time": 0.186,
      "row_count": 30,
      "memory_start_mb": 83.72,
      "memory_end_mb": 83.72,
      "memory_delta_mb": 0.0,
      "timestamp": "2025-11-20T06:12:21.840367",
      "query_preview": "\n        SELECT\n            data_value,\n            time_value\n        FROM exchange_rate\n        WHERE stat_code = '731Y001'\n            AND item_code1 = '0000001'\n            AND cycle = 'D'\n       ..."
    },
    {
      "name": "Unnamed Query",
      "execution_time": 0.181,
      "row_count": 4,
      "memory_start_mb": 83.72,
      "memory_end_mb": 83.72,
      "memory_delta_mb": 0.0,
      "timestamp": "2025-11-20T06:12:22.112837",
      "query_preview": "\n        SELECT\n            data_value,\n            time_value\n        FROM bok_economic_indicators\n        WHERE stat_code = '901Y009'\n            AND cycle = 'M'\n        ORDER BY time_value DESC\n   ..."
    },
    {
      "name": "Unnamed Query",
      "execution_time": 0.184,
      "row_count": 1,
      "memory_start_mb": 83.72,
      "memory_end_mb": 83.72,
      "memory_delta_mb": 0.0,
      "timestamp": "2025-11-20T06:12:22.388669",
      "query_preview": "\n            WITH market_data AS (\n                SELECT\n                    close,\n                    LAG(close, 20) OVER (ORDER BY date) as close_20d_ago,\n                    LAG(close, 60) OVER (..."
    },
    {
      "name": "Unnamed Query",
      "execution_time": 0.094,
      "row_count": 1,
      "memory_start_mb": 83.72,
      "memory_end_mb": 83.72,
      "memory_delta_mb": 0.0,
      "timestamp": "2025-11-20T06:12:22.572862",
      "query_preview": "\n            WITH market_data AS (\n                SELECT\n                    close,\n                    LAG(close, 20) OVER (ORDER BY date) as close_20d_ago,\n                    LAG(close, 60) OVER (..."
    },
    {
      "name": "Unnamed Query",
      "execution_time": 1.854,
      "row_count": 163,
      "memory_start_mb": 83.72,
      "memory_end_mb": 83.74,
      "memory_delta_mb": 0.02,
      "timestamp": "2025-11-20T06:12:24.517410",
      "query_preview": "\n        WITH stock_returns AS (\n            SELECT\n                d.industry,\n                i.symbol,\n                i.date,\n                i.close,\n                LAG(i.close, 20) OVER (PARTIT..."
    },
    {
      "name": "Query 1: Basic Info",
      "execution_time": 2.276,
      "row_count": 2645,
      "memory_start_mb": 83.74,
      "memory_end_mb": 83.77,
      "memory_delta_mb": 0.03,
      "timestamp": "2025-11-20T06:12:26.905335",
      "query_preview": "\n        SELECT symbol, exchange, industry, theme\n        FROM kr_stock_detail\n        WHERE symbol = ANY($1)\n        "
    },
    {
      "name": "Query 2: Combined Market Data (Latest + Liquidity + Volatility)",
      "execution_time": 2.901,
      "row_count": 2759,
      "memory_start_mb": 83.84,
      "memory_end_mb": 84.02,
      "memory_delta_mb": 0.17,
      "timestamp": "2025-11-20T06:12:29.899963",
      "query_preview": "\n        WITH latest_data AS (\n            SELECT DISTINCT ON (symbol)\n                symbol,\n                market_cap,\n                close,\n                date\n            FROM kr_intraday_tota..."
    }
  ],
  "phases": {
    "phase1": 3.815775,
    "phase2": 5.370115,
    "phase2_5": 0.00935,
    "phase3": 0.077956
  },
  "memory_snapshots": [
    {
      "label": "Start",
      "timestamp": "2025-11-20T06:12:20.813468",
      "rss_mb": 83.72,
      "vms_mb": 439.52,
      "percent": 0.53
    },
    {
      "label": "After Phase 1",
      "timestamp": "2025-11-20T06:12:24.629415",
      "rss_mb": 83.74,
      "vms_mb": 439.53,
      "percent": 0.53
    },
    {
      "label": "After Phase 2",
      "timestamp": "2025-11-20T06:12:29.999770",
      "rss_mb": 84.02,
      "vms_mb": 439.69,
      "percent": 0.53
    },
    {
      "label": "After Phase 2.5",
      "timestamp": "2025-11-20T06:12:30.009237",
      "rss_mb": 84.64,
      "vms_mb": 439.93,
      "percent": 0.54
    },
    {
      "label": "After Phase 3",
      "timestamp": "2025-11-20T06:12:30.087372",
      "rss_mb": 84.64,
      "vms_mb": 439.93,
      "percent": 0.54
    }
  ],
  "start_time": "2025-11-20T06:12:20.813337",
  "end_time": "2025-11-20T06:12:30.087439",
  "total_time": 9.274102,
  "total_stocks": 2759,
  "processed_stocks": 2645,
  "skipped_stocks": 114
}