{
  "queries": [
    {
      "name": "Unnamed Query",
      "execution_time": 0.154,
      "row_count": 1,
      "memory_start_mb": 83.15,
      "memory_end_mb": 83.16,
      "memory_delta_mb": 0.01,
      "timestamp": "2025-11-17T02:55:10.618249",
      "query_preview": "\n        WITH gdp_data AS (\n            SELECT\n                time_value,\n                data_value as gdp_growth,\n                LAG(data_value, 1) OVER (ORDER BY time_value) as prev_gdp,\n        ..."
    },
    {
      "name": "Unnamed Query",
      "execution_time": 0.149,
      "row_count": 90,
      "memory_start_mb": 83.16,
      "memory_end_mb": 83.16,
      "memory_delta_mb": 0.0,
      "timestamp": "2025-11-17T02:55:10.839893",
      "query_preview": "\n        SELECT\n            data_value,\n            time_value\n        FROM bok_economic_indicators\n        WHERE stat_code = '722Y001'\n            AND cycle = 'D'\n        ORDER BY time_value DESC\n   ..."
    },
    {
      "name": "Unnamed Query",
      "execution_time": 0.151,
      "row_count": 3,
      "memory_start_mb": 83.16,
      "memory_end_mb": 83.16,
      "memory_delta_mb": 0.0,
      "timestamp": "2025-11-17T02:55:11.063001",
      "query_preview": "\n        SELECT\n            data_value\n        FROM bok_economic_indicators\n        WHERE stat_code = '513Y001'\n            AND item_name1 LIKE '%경제심리지수%'\n            AND cycle = 'M'\n        ORDER BY ..."
    },
    {
      "name": "Unnamed Query",
      "execution_time": 0.153,
      "row_count": 30,
      "memory_start_mb": 83.16,
      "memory_end_mb": 83.17,
      "memory_delta_mb": 0.01,
      "timestamp": "2025-11-17T02:55:11.290144",
      "query_preview": "\n        SELECT\n            data_value,\n            time_value\n        FROM exchange_rate\n        WHERE stat_code = '731Y001'\n            AND item_code1 = '0000001'\n            AND cycle = 'D'\n       ..."
    },
    {
      "name": "Unnamed Query",
      "execution_time": 0.15,
      "row_count": 4,
      "memory_start_mb": 83.17,
      "memory_end_mb": 83.17,
      "memory_delta_mb": 0.0,
      "timestamp": "2025-11-17T02:55:11.515416",
      "query_preview": "\n        SELECT\n            data_value,\n            time_value\n        FROM bok_economic_indicators\n        WHERE stat_code = '901Y009'\n            AND cycle = 'M'\n        ORDER BY time_value DESC\n   ..."
    },
    {
      "name": "Unnamed Query",
      "execution_time": 0.161,
      "row_count": 1,
      "memory_start_mb": 83.17,
      "memory_end_mb": 83.17,
      "memory_delta_mb": 0.0,
      "timestamp": "2025-11-17T02:55:11.751579",
      "query_preview": "\n            WITH market_data AS (\n                SELECT\n                    close,\n                    LAG(close, 20) OVER (ORDER BY date) as close_20d_ago,\n                    LAG(close, 60) OVER (..."
    },
    {
      "name": "Unnamed Query",
      "execution_time": 0.081,
      "row_count": 1,
      "memory_start_mb": 83.17,
      "memory_end_mb": 83.17,
      "memory_delta_mb": 0.0,
      "timestamp": "2025-11-17T02:55:11.911659",
      "query_preview": "\n            WITH market_data AS (\n                SELECT\n                    close,\n                    LAG(close, 20) OVER (ORDER BY date) as close_20d_ago,\n                    LAG(close, 60) OVER (..."
    },
    {
      "name": "Unnamed Query",
      "execution_time": 1.516,
      "row_count": 163,
      "memory_start_mb": 83.17,
      "memory_end_mb": 83.21,
      "memory_delta_mb": 0.04,
      "timestamp": "2025-11-17T02:55:13.507139",
      "query_preview": "\n        WITH stock_returns AS (\n            SELECT\n                d.industry,\n                i.symbol,\n                i.date,\n                i.close,\n                LAG(i.close, 20) OVER (PARTIT..."
    },
    {
      "name": "Query 1: Basic Info",
      "execution_time": 0.553,
      "row_count": 2645,
      "memory_start_mb": 83.21,
      "memory_end_mb": 83.39,
      "memory_delta_mb": 0.19,
      "timestamp": "2025-11-17T02:55:14.137294",
      "query_preview": "\n        SELECT symbol, exchange, industry, theme\n        FROM kr_stock_detail\n        WHERE symbol = ANY($1)\n        "
    },
    {
      "name": "Query 2: Combined Market Data (Latest + Liquidity + Volatility)",
      "execution_time": 1.994,
      "row_count": 2759,
      "memory_start_mb": 83.4,
      "memory_end_mb": 83.57,
      "memory_delta_mb": 0.17,
      "timestamp": "2025-11-17T02:55:16.210680",
      "query_preview": "\n        WITH latest_data AS (\n            SELECT DISTINCT ON (symbol)\n                symbol,\n                market_cap,\n                close,\n                date\n            FROM kr_intraday_tota..."
    }
  ],
  "phases": {
    "phase1": 3.119972,
    "phase2": 2.71009,
    "phase2_5": 0.008457,
    "phase3": 0.076239
  },
  "memory_snapshots": [
    {
      "label": "Start",
      "timestamp": "2025-11-17T02:55:10.463801",
      "rss_mb": 83.15,
      "vms_mb": 434.39,
      "percent": 0.53
    },
    {
      "label": "After Phase 1",
      "timestamp": "2025-11-17T02:55:13.583932",
      "rss_mb": 83.21,
      "vms_mb": 434.4,
      "percent": 0.53
    },
    {
      "label": "After Phase 2",
      "timestamp": "2025-11-17T02:55:16.294185",
      "rss_mb": 83.57,
      "vms_mb": 434.92,
      "percent": 0.53
    },
    {
      "label": "After Phase 2.5",
      "timestamp": "2025-11-17T02:55:16.302760",
      "rss_mb": 84.13,
      "vms_mb": 435.04,
      "percent": 0.53
    },
    {
      "label": "After Phase 3",
      "timestamp": "2025-11-17T02:55:16.379218",
      "rss_mb": 84.13,
      "vms_mb": 435.04,
      "percent": 0.53
    }
  ],
  "start_time": "2025-11-17T02:55:10.463705",
  "end_time": "2025-11-17T02:55:16.379268",
  "total_time": 5.915563,
  "total_stocks": 2759,
  "processed_stocks": 2645,
  "skipped_stocks": 114
}